django_chapa/__init__.py
django_chapa/admin.py
django_chapa/api.py
django_chapa/apps.py
django_chapa/migrations/0001_initial.py
django_chapa/migrations/__init__.py
django_chapa/models.py
django_chapa/tests.py
django_chapa/urls.py
django_chapa/views.py
django_chapa-1.0.3.dist-info/WHEEL
django_chapa-1.0.3.dist-info/METADATA
django_chapa-1.0.3.dist-info/RECORD
