Metadata-Version: 2.1
Name: django-chapa
Version: 1.0.3
Summary: Unofficial Django Implementation For Chapa Payment Gateway
Home-page: https://github.com/abelayalew/django-chapa
License: MIT
Author: abelayalew
Author-email: abelayalew81@gmail.com
Requires-Python: >=3.8,<4.0
Classifier: License :: OSI Approved :: MIT License
Classifier: Programming Language :: Python :: 3
Classifier: Programming Language :: Python :: 3.10
Classifier: Programming Language :: Python :: 3.8
Classifier: Programming Language :: Python :: 3.9
Requires-Dist: Django (>=4.1,<5.0)
Requires-Dist: requests (>=2.28.1,<3.0.0)
Project-URL: Repository, https://github.com/abelayalew/django-chapa
